odoo/addons/website_sale_filter_product_brand/README.rst
odoo/addons/website_sale_filter_product_brand/__init__.py
odoo/addons/website_sale_filter_product_brand/__manifest__.py
odoo/addons/website_sale_filter_product_brand/controllers/__init__.py
odoo/addons/website_sale_filter_product_brand/controllers/website_sale.py
odoo/addons/website_sale_filter_product_brand/demo/product_brand_demo.xml
odoo/addons/website_sale_filter_product_brand/demo/product_product_demo.xml
odoo/addons/website_sale_filter_product_brand/i18n/es.po
odoo/addons/website_sale_filter_product_brand/i18n/it.po
odoo/addons/website_sale_filter_product_brand/i18n/website_sale_filter_product_brand.pot
odoo/addons/website_sale_filter_product_brand/readme/CONTRIBUTORS.rst
odoo/addons/website_sale_filter_product_brand/readme/DESCRIPTION.rst
odoo/addons/website_sale_filter_product_brand/readme/USAGE.rst
odoo/addons/website_sale_filter_product_brand/static/description/icon.png
odoo/addons/website_sale_filter_product_brand/static/description/index.html
odoo/addons/website_sale_filter_product_brand/static/src/js/website_sale_product_brand_filter.js
odoo/addons/website_sale_filter_product_brand/static/src/scss/website_sale_product_brand_filter.scss
odoo/addons/website_sale_filter_product_brand/static/src/tests/tours/test_website_sale_filter_brand.js
odoo/addons/website_sale_filter_product_brand/tests/__init__.py
odoo/addons/website_sale_filter_product_brand/tests/test_website_sale_filter_brand.py
odoo/addons/website_sale_filter_product_brand/views/assets.xml
odoo/addons/website_sale_filter_product_brand/views/templates.xml
odoo14_addon_website_sale_filter_product_brand-14.0.1.0.2.dist-info/METADATA
odoo14_addon_website_sale_filter_product_brand-14.0.1.0.2.dist-info/WHEEL
odoo14_addon_website_sale_filter_product_brand-14.0.1.0.2.dist-info/top_level.txt
odoo14_addon_website_sale_filter_product_brand-14.0.1.0.2.dist-info/RECORD
